setup.py
probabilities_test_higor/Binomialdistribution.py
probabilities_test_higor/Gaussiandistribution.py
probabilities_test_higor/Generaldistribution.py
probabilities_test_higor/__init__.py
probabilities_test_higor.egg-info/PKG-INFO
probabilities_test_higor.egg-info/SOURCES.txt
probabilities_test_higor.egg-info/dependency_links.txt
probabilities_test_higor.egg-info/not-zip-safe
probabilities_test_higor.egg-info/top_level.txt