Metadata-Version: 1.0
Name: probabilities-test-higor
Version: 1.2
Summary: Gaussian and Binomial distributions
Home-page: UNKNOWN
Author: Higor de Faria
Author-email: UNKNOWN
License: UNKNOWN
Platform: UNKNOWN
